MANIFEST.in
setup.cfg
setup.py
_ccfreeze_loader/__init__.py
_ccfreeze_loader/console.c
_ccfreeze_loader/consolew.c
_ccfreeze_loader/getpath.c
_ccfreeze_loader/loader_impl.h
ccfreeze_loader.egg-info/PKG-INFO
ccfreeze_loader.egg-info/SOURCES.txt
ccfreeze_loader.egg-info/dependency_links.txt
ccfreeze_loader.egg-info/not-zip-safe
ccfreeze_loader.egg-info/top_level.txt