Metadata-Version: 1.1
Name: ccfreeze-loader
Version: 1.1.2
Summary: provide binary loaders for ccfreeze
Home-page: http://pypi.python.org/pypi/ccfreeze/
Author: Josh Brown
Author-email: cars1189@aol.com
License: zlib/libpng license
Platform: Linux Windows
Classifier: Development Status :: 5 - Production/Stable
Classifier: License :: OSI Approved :: zlib/libpng License
Classifier: Intended Audience :: Developers
Classifier: Programming Language :: Python
Classifier: Programming Language :: Python :: 2
Classifier: Programming Language :: Python :: 2.7
Classifier: Topic :: Software Development :: Build Tools
Classifier: Topic :: System :: Software Distribution
